pytest_sa_pg/__init__.py
pytest_sa_pg/db.py
pytest_sa_pg/fixture.py
pytest_sa_pg-0.3.2.dist-info/METADATA
pytest_sa_pg-0.3.2.dist-info/RECORD
pytest_sa_pg-0.3.2.dist-info/WHEEL
pytest_sa_pg-0.3.2.dist-info/top_level.txt
