Metadata-Version: 2.1
Name: pytest-sa-pg
Version: 0.3.2
Summary: 
Requires-Dist: psycopg2-binary
Requires-Dist: sqlalchemy
